dmeta/__init__.py
dmeta/__main__.py
dmeta/errors.py
dmeta/functions.py
dmeta/params.py
dmeta/util.py
dmeta-0.4.dist-info/licenses/AUTHORS.md
dmeta-0.4.dist-info/licenses/LICENSE
dmeta-0.4.dist-info/METADATA
dmeta-0.4.dist-info/WHEEL
dmeta-0.4.dist-info/entry_points.txt
dmeta-0.4.dist-info/top_level.txt
dmeta-0.4.dist-info/RECORD
